{
  "id": "266617",
  "type": "report",
  "source_id": "audio52",
  "url": "https://www.52audio.com/archives/266617.html",
  "title": "MONSTER魔声XKO07开放式耳机",
  "brand": "",
  "model": "MONSTER魔声XKO07",
  "category": "开放式耳机",
  "published_at": "2026-01-20",
  "author": "Wen5",
  "summary": "MONSTER魔声是一家成立于1979年的国际知名老牌音频厂商，致力于开发设计创造性产品以提升音乐音质。XKO […]",
  "captured_at": "2026-07-02T08:58:41+00:00",
  "views": {
    "market": {
      "brand": "",
      "model": "MONSTER魔声XKO07",
      "category": "开放式耳机",
      "launch_date": null,
      "price_cny": null,
      "price_note": "",
      "selling_points": [
        "IP5513内置MCU，可灵活定制4/3/2/1颗LED或188数码管电量显示。",
        "IP5513的高集成度与丰富功能，使其在应用时仅需极少的外围器件，并有效减小整体方案的尺寸，降低BOM成本。",
        "INJOINIC英集芯IP5513是一款集成5V升压转换器、锂电池充电管理、电池电量指示的多功能电源管理SoC，为TWS蓝牙耳机充电仓提供完整的电源解决方案。",
        "英集芯IP5513可实现TWS对耳独立入仓检测，检测到耳机入仓后自动进入耳机充电模式，耳机充满后自动进入休眠状态，静态电流最低可降至30uA。",
        "主板上，采用了INJOINIC英集芯IP5513电源管理SoC，集成MCU、5V升压转换器、锂电池充电管理、电池电量指示等多功能，单芯片为充电盒提供完整的电源解决方案。",
        "INJOINIC英集芯IP5513详细资料图。"
      ],
      "scenarios": [
        "游戏",
        "通话"
      ],
      "positioning_summary": "IP5513内置MCU，可灵活定制4/3/2/1颗LED或188数码管电量显示。"
    },
    "cost": {
      "major_parts": [
        "充电仓",
        "电池",
        "主板/PCBA",
        "喇叭单元",
        "麦克风",
        "降噪系统",
        "天线"
      ],
      "chip_modules": [
        {
          "part": "芯片/模组",
          "brand": "",
          "model": "JL7006",
          "qty_hint": ""
        },
        {
          "part": "芯片/模组",
          "brand": "",
          "model": "JL7006",
          "qty_hint": ""
        }
      ],
      "packaging_notes": [
        "打开包装盒，取出内部所有物品，包括了主机、充电线和说明书。"
      ],
      "process_hints": [
        "充电盒内部主要电路一览，电池导线与主板焊接。",
        "腔体内部主板单元结构一览，与导线焊接，打胶防护。",
        "断开电池与主板焊接的导线。"
      ]
    },
    "structure": {
      "form_factor": "开放式耳机",
      "materials": [
        "硅胶"
      ],
      "ip_rating": "IP5",
      "weight_g": "95.9g",
      "dimensions": [
        "在功能配置上，MONSTER魔声XKO07开放式耳机搭载16.2mm大振膜动圈喇叭，支持数字增强技术，提供360°环绕立体声；支持音乐/游戏双模式，满足不同场景需求；搭载高性能麦克风，提供精准拾音，带来清晰通话。",
        "蓝牙版本：V5.3，传输距离：10m，喇叭直径：16.2mm，喇叭阻抗：16Ω，灵敏度：85±3dB，频响范围：20Hz-20kHz，电池容量（充电盒）：390mAh 3.7V，电池容量（耳机）：60mAh 3.7V，充电时间：约1.5h，配合充电盒播放时间：约16小时，制造商：深圳悦享无线科技有限公司。",
        "IP5513的高集成度与丰富功能，使其在应用时仅需极少的外围器件，并有效减小整体方案的尺寸，降低BOM成本。"
      ],
      "wear_design": [
        "XKO07开放式耳机是该品牌旗下一款高性价比产品，外观上耳机采用耳挂式设计，提供持久的舒适聆听体验；充电盒采用人工纺织毛绒材质，触感柔软，不易划伤。",
        "MONSTER魔声XKO07开放式耳机整体外观一览，耳机采用了耳挂式设计，提供舒适的开放式聆听体验。",
        "耳挂整体通过硅胶材质包裹，佩戴舒适亲肤。",
        "耳机内侧外观一览，音腔采用了光滑圆润的质感，佩戴舒适贴合耳廓。"
      ],
      "assembly_notes": [
        "MONSTER魔声是一家成立于1979年的国际知名老牌音频厂商，致力于开发设计创造性产品以提升音乐音质。XKO07开放式耳机是该品牌旗下一款高性价比产品，外观上耳机采用耳挂式设计，提供持久的舒适聆听体验；充电盒采用人工纺织毛绒材质，触感柔软，不易划伤。",
        "包装盒背面介绍了产品的主要功能特点和参数信息，以及部分公司信息。蓝牙版本：V5.3，传输距离：10m，喇叭直径：16.2mm，喇叭阻抗：16Ω，灵敏度：85±3dB，频响范围：20Hz-20kHz，电池容量（充电盒）：390mAh 3.7V，电池容量（耳机）：60mAh 3.7V，充电时间：约1.5h，配合充电盒播放时间：约16小时，制造商：深圳悦享无线科技有限公司。",
        "座舱底部结构一览，通过螺丝固定主板单元。",
        "在功能配置上，MONSTER魔声XKO07开放式耳机搭载16.2mm大振膜动圈喇叭，支持数字增强技术，提供360°环绕立体声；支持音乐/游戏双模式，满足不同场景需求；搭载高性能麦克风，提供精准拾音，带来清晰通话。续航方面，支持单次约9小时，综合约27小时的音乐聆听。下面就来看看这款产品的详细拆解报告吧~",
        "在功能配置上，MONSTER魔声XKO07开放式耳机搭载16.2mm大振膜动圈喇叭，支持数字增强技术，提供360°环绕立体声；支持音乐/游戏双模式，满足不同场景需求；搭载高性能麦克风，提供精准拾音，带来清晰通话。续航方面，支持单次约9小时，综合约27小时的音乐聆听。下面就来看看这款产品的详细拆解报告吧~",
        "我爱音频网此前还拆解过MONSTER魔声AIRMARS XKT30、魔声Open Ear 101、魔声Open Ear Lite开放式耳机，魔声Monster Aria ANC钻石之泪、魔声MISSION V1 TWS耳机、魔声Clarity 108 ANC TWS耳机、魔声CLARITY 8.0 ANC真无线耳机、魔声MONSTER iSport ACHIEVE 脖挂蓝牙耳机等。"
      ]
    },
    "hardware": {
      "specs": [
        {
          "part": "充电接口",
          "brand": "",
          "model": "",
          "value": "充电线采用了USB-A to Type-C插头。",
          "unit": "",
          "source_ref": "text"
        },
        {
          "part": "充电接口",
          "brand": "",
          "model": "",
          "value": "充电盒背部设置有Type-C充电接口和三颗指示灯。",
          "unit": "",
          "source_ref": "text"
        },
        {
          "part": "充电接口",
          "brand": "",
          "model": "",
          "value": "Type-C充电母座特写。",
          "unit": "",
          "source_ref": "text"
        },
        {
          "part": "充电接口",
          "brand": "",
          "model": "Type-C",
          "value": "Type-C",
          "unit": "",
          "source_ref": "text"
        },
        {
          "part": "充电接口",
          "brand": "",
          "model": "USB-A",
          "value": "USB-A",
          "unit": "",
          "source_ref": "text"
        },
        {
          "part": "标记/认证",
          "brand": "",
          "model": "",
          "value": "蓝牙版本：V5.3，传输距离：10m，喇叭直径：16.2mm，喇叭阻抗：16Ω，灵敏度：85±3dB，频响范围：20Hz-20kHz，电池容量（充电盒）：390mAh 3.7V，电池容量（耳机）：60mAh 3.7V，充电时间：约1.5h，配合充电盒播放时间：约16小时，制造商：深圳悦享无线科技有限公司。",
          "unit": "",
          "source_ref": "text"
        },
        {
          "part": "标记/认证",
          "brand": "",
          "model": "",
          "value": "我爱音频网使用\nCHARGERLAB POWER-Z KM003C\n对MONSTER魔声XKO07开放式耳机进行充电测试，输入功率约为1.64W。",
          "unit": "",
          "source_ref": "text"
        },
        {
          "part": "标记/认证",
          "brand": "",
          "model": "",
          "value": "充电盒内置锂电池型号：ST 482535，标称电压：3.7V，额定容量：390mAh 1.443Wh，来自ST神通天下。",
          "unit": "",
          "source_ref": "text"
        },
        {
          "part": "标记/认证",
          "brand": "",
          "model": "",
          "value": "INJOINIC英集芯IP5513是一款集成5V升压转换器、锂电池充电管理、电池电量指示的多功能电源管理SoC，为TWS蓝牙耳机充电仓提供完整的电源解决方案。",
          "unit": "",
          "source_ref": "text"
        },
        {
          "part": "标记/认证",
          "brand": "",
          "model": "",
          "value": "IP5513的高集成度与丰富功能，使其在应用时仅需极少的外围器件，并有效减小整体方案的尺寸，降低BOM成本。",
          "unit": "",
          "source_ref": "text"
        },
        {
          "part": "标记/认证",
          "brand": "",
          "model": "",
          "value": "英集芯IP5513内置一个5V输出、同步整流的升压DC-DC，功率管内置，提供最大300mA输出电流，升压效率高至93%；IP5513的线性充电提供最大500mA充电电流， 可灵活配置最大充电电流。",
          "unit": "",
          "source_ref": "text"
        },
        {
          "part": "标记/认证",
          "brand": "",
          "model": "",
          "value": "英集芯IP5513可实现TWS对耳独立入仓检测，检测到耳机入仓后自动进入耳机充电模式，耳机充满后自动进入休眠状态，静态电流最低可降至30uA。",
          "unit": "",
          "source_ref": "text"
        },
        {
          "part": "标记/认证",
          "brand": "",
          "model": "",
          "value": "IP5513内置MCU，可灵活定制4/3/2/1颗LED或188数码管电量显示。",
          "unit": "",
          "source_ref": "text"
        },
        {
          "part": "标记/认证",
          "brand": "",
          "model": "",
          "value": "INJOINIC英集芯IP5513详细资料图。",
          "unit": "",
          "source_ref": "text"
        },
        {
          "part": "标记/认证",
          "brand": "",
          "model": "",
          "value": "耳机内置锂电池型号：ST 601215，标称电压：3.7V，额定能量：0.24Wh，同样来自ST神通天下。",
          "unit": "",
          "source_ref": "text"
        },
        {
          "part": "标记/认证",
          "brand": "",
          "model": "",
          "value": "主板上，采用了INJOINIC英集芯IP5513电源管理SoC，集成MCU、5V升压转换器、锂电池充电管理、电池电量指示等多功能，单芯片为充电盒提供完整的电源解决方案。",
          "unit": "",
          "source_ref": "text"
        },
        {
          "part": "电池",
          "brand": "",
          "model": "",
          "value": "390",
          "unit": "mAh",
          "source_ref": "text"
        }
      ]
    },
    "software": {
      "bluetooth_version": null,
      "codecs": [],
      "multipoint": [],
      "app_name": "",
      "app_features": [
        "IP5513的高集成度与丰富功能，使其在应用时仅需极少的外围器件，并有效减小整体方案的尺寸，降低BOM成本。"
      ],
      "ota_support": [],
      "latency_notes": []
    }
  }
}