{
  "video_id": "269547",
  "status": "empty",
  "method": "none",
  "transcript": "",
  "transcript_chars": 0,
  "summary": "",
  "resolved_url": "https://www.bilibili.com/video/BV1j8PWzREcM",
  "enriched_at": "2026-07-10T02:28:36+00:00",
  "cookies_from_browser": "edge",
  "degraded_reason": "yt-dlp audio/subtitle failed: [BiliBili] Extracting URL: https://www.bilibili.com/video/BV1j8PWzREcM\n[BiliBili] 1j8PWzREcM: Downloading webpage\nExtracting cookies from edge\nERROR: Could not copy Chrome cookie database. See  https://github.com/yt-dlp/yt-dlp/issues/7271  for more info\nERROR: Could not copy Chrome cookie database. See  https://github.com/yt-dlp/yt-dlp/issues/7271  for more info\n"
}